[
  {
    "ContainingType": "ManagementSystem.WebAPI.Controllers.CategoryController",
    "Method": "UpdateCategory",
    "RelativePath": "api/Category/{id}",
    "HttpMethod": "PUT",
    "IsController": true,
    "Order": 0,
    "Parameters": [
      {
        "Name": "id",
        "Type": "System.Int32",
        "IsRequired": true
      },
      {
        "Name": "dto",
        "Type": "ManagementSystem.BLL.DTO.CategoryDtos.UpdateCategoryRequestDto",
        "IsRequired": true
      }
    ],
    "ReturnTypes": []
  },
  {
    "ContainingType": "ManagementSystem.WebAPI.Controllers.CategoryController",
    "Method": "DeleteCategory",
    "RelativePath": "api/Category/{id}",
    "HttpMethod": "DELETE",
    "IsController": true,
    "Order": 0,
    "Parameters": [
      {
        "Name": "id",
        "Type": "System.Int32",
        "IsRequired": true
      }
    ],
    "ReturnTypes": []
  },
  {
    "ContainingType": "ManagementSystem.WebAPI.Controllers.CategoryController",
    "Method": "CreateCategory",
    "RelativePath": "api/Category/create-category",
    "HttpMethod": "POST",
    "IsController": true,
    "Order": 0,
    "Parameters": [
      {
        "Name": "dto",
        "Type": "ManagementSystem.BLL.DTO.CategoryDtos.CreateCategoryRequestDto",
        "IsRequired": true
      }
    ],
    "ReturnTypes": []
  },
  {
    "ContainingType": "ManagementSystem.WebAPI.Controllers.CategoryController",
    "Method": "GetCategories",
    "RelativePath": "api/Category/get-categories",
    "HttpMethod": "GET",
    "IsController": true,
    "Order": 0,
    "Parameters": [],
    "ReturnTypes": []
  },
  {
    "ContainingType": "ManagementSystem.WebAPI.Controllers.ProductController",
    "Method": "GetProducts",
    "RelativePath": "api/Product",
    "HttpMethod": "GET",
    "IsController": true,
    "Order": 0,
    "Parameters": [],
    "ReturnTypes": []
  },
  {
    "ContainingType": "ManagementSystem.WebAPI.Controllers.ProductController",
    "Method": "CreateProduct",
    "RelativePath": "api/Product",
    "HttpMethod": "POST",
    "IsController": true,
    "Order": 0,
    "Parameters": [
      {
        "Name": "dto",
        "Type": "ManagementSystem.BLL.DTO.ProductDtos.CreateProductRequestDto",
        "IsRequired": true
      }
    ],
    "ReturnTypes": []
  },
  {
    "ContainingType": "ManagementSystem.WebAPI.Controllers.ProductController",
    "Method": "UpdateProduct",
    "RelativePath": "api/Product/{id}",
    "HttpMethod": "PUT",
    "IsController": true,
    "Order": 0,
    "Parameters": [
      {
        "Name": "id",
        "Type": "System.Int32",
        "IsRequired": true
      },
      {
        "Name": "dto",
        "Type": "ManagementSystem.BLL.DTO.ProductDtos.UpdateProductRequestDto",
        "IsRequired": true
      }
    ],
    "ReturnTypes": []
  },
  {
    "ContainingType": "ManagementSystem.WebAPI.Controllers.ProductController",
    "Method": "DeleteProduct",
    "RelativePath": "api/Product/{id}",
    "HttpMethod": "DELETE",
    "IsController": true,
    "Order": 0,
    "Parameters": [
      {
        "Name": "id",
        "Type": "System.Int32",
        "IsRequired": true
      }
    ],
    "ReturnTypes": []
  },
  {
    "ContainingType": "ManagementSystem.WebAPI.Controllers.ProductController",
    "Method": "GetProductCategories",
    "RelativePath": "api/Product/get-product-category",
    "HttpMethod": "GET",
    "IsController": true,
    "Order": 0,
    "Parameters": [],
    "ReturnTypes": []
  }
]